tests/__init__.py
thread_with_results/__init__.py
thread_with_results/exceptions.py
thread_with_results/thread.py
thread_with_results-1.0.1.dist-info/LICENSE
thread_with_results-1.0.1.dist-info/METADATA
thread_with_results-1.0.1.dist-info/WHEEL
thread_with_results-1.0.1.dist-info/top_level.txt
thread_with_results-1.0.1.dist-info/RECORD
